laicrypto_gui-0.1.0.dist-info/licenses/LICENSE
laigui/gui.py
laicrypto_gui-0.1.0.dist-info/METADATA
laicrypto_gui-0.1.0.dist-info/WHEEL
laicrypto_gui-0.1.0.dist-info/top_level.txt
laicrypto_gui-0.1.0.dist-info/RECORD
